wbxml
