Metadata-Version: 1.1
Name: wbxml
Version: 0.1.1
Summary: Python wrapper for libwbxml
Home-page: https://github.com/infoshift/python-wbxml
Author: Jezeniel Zapanta
Author-email: jezeniel@infoshiftinc.com
License: MIT
Keywords: wbxml,xml,mobile
Platform: UNKNOWN
Classifier: Intended Audience :: Developers
Classifier: Topic :: Software Development :: Libraries
Classifier: License :: OSI Approved :: MIT License
Classifier: Programming Language :: Python :: 2.7
